finlight_client/__init__.py
finlight_client/api_client.py
finlight_client/articles.py
finlight_client/models.py
finlight_client/sources.py
finlight_client/webhook_service.py
finlight_client/websocket_client.py
finlight_client-2.0.3.dist-info/licenses/LICENSE
tests/__init__.py
tests/test_webhook_service.py
finlight_client-2.0.3.dist-info/METADATA
finlight_client-2.0.3.dist-info/WHEEL
finlight_client-2.0.3.dist-info/top_level.txt
finlight_client-2.0.3.dist-info/RECORD
