Metadata-Version: 2.4
Name: finlight-client
Version: 2.0.3
Summary: Python client for the Finlight API
Home-page: https://github.com/jubeiargh/finlight-client-py
Author: Ali Büyükkakac
Author-email: ali@finlight.me
Classifier: Programming Language :: Python :: 3
Classifier: License :: OSI Approved :: MIT License
Classifier: Operating System :: OS Independent
Requires-Python: >=3.7
License-File: LICENSE
Requires-Dist: requests
Requires-Dist: websockets>=14.0
Requires-Dist: pydantic<3.0,>=2.7
Dynamic: author
Dynamic: author-email
Dynamic: classifier
Dynamic: description
Dynamic: description-content-type
Dynamic: home-page
Dynamic: license-file
Dynamic: requires-dist
Dynamic: requires-python
Dynamic: summary
